opus_adstator/__init__.py
opus_adstator/file_io.py
opus_adstator/utils.py
opus_adstator-1.1.dist-info/METADATA
opus_adstator-1.1.dist-info/WHEEL
opus_adstator-1.1.dist-info/licenses/LICENSE
opus_adstator-1.1.dist-info/RECORD
