Metadata-Version: 2.1
Name: opus-adstator
Version: 1.1
Summary: Additional helpers and utilities for the magnum-opus eco-system.
Project-URL: Homepage, https://github.com/nicc777/opus-adstator
Project-URL: Documentation, https://github.com/nicc777/opus-adstator
Project-URL: Repository, https://github.com/nicc777/opus-adstator
Project-URL: Issues, https://github.com/nicc777/opus-adstator/issues
Project-URL: Changelog, https://raw.githubusercontent.com/nicc777/opus-adstator/main/CHANGELOG.md
Author-email: Nico Coetzee <nicc777@gmail.com>
Maintainer-email: Nico Coetzee <nicc777@gmail.com>
License: MIT License
License-File: LICENSE
Classifier: Development Status :: 3 - Alpha
Classifier: Intended Audience :: Developers
Classifier: License :: OSI Approved :: MIT License
Classifier: Programming Language :: Python :: 3
Classifier: Programming Language :: Python :: 3.8
Classifier: Programming Language :: Python :: 3.9
Classifier: Programming Language :: Python :: 3.10
Classifier: Programming Language :: Python :: 3.11
Classifier: Programming Language :: Python :: 3.12
Requires-Python: >=3.8
